quizgen/quizgen.py
quizgen/scripts/convert_questions.py
quizgen/scripts/convert_questions_batch.py
quizgen/scripts/generate_embeddings.py
quizgen/scripts/generate_embeddings_batch.py
quizgen/scripts/generate_questions.py
quizgen/scripts/generate_questions_batch.py
quizgen/scripts/import_to_anki.py
quizgen/scripts/thin_out_questions.py
quizgen_ai-1.0.2.dist-info/LICENSE
quizgen_ai-1.0.2.dist-info/METADATA
quizgen_ai-1.0.2.dist-info/WHEEL
quizgen_ai-1.0.2.dist-info/entry_points.txt
quizgen_ai-1.0.2.dist-info/RECORD
