Metadata-Version: 2.1
Name: quizgen-ai
Version: 1.0.2
Summary: AI-Powered Question Generation Tool
Home-page: https://github.com/kdunee/quizgen
License: MIT
Keywords: ai,quiz,anki,llm
Author: Kosma Dunikowski
Author-email: kosmadunikowski@gmail.com
Requires-Python: >=3.10,<4.0
Classifier: License :: OSI Approved :: MIT License
Classifier: Programming Language :: Python :: 3
Classifier: Programming Language :: Python :: 3.10
Classifier: Programming Language :: Python :: 3.11
Classifier: Programming Language :: Python :: 3.12
Requires-Dist: numpy (>=2.1.2,<3.0.0)
Requires-Dist: openai (>=1.47.1,<2.0.0)
Requires-Dist: scikit-learn (>=1.5.2,<2.0.0)
Requires-Dist: tqdm (>=4.66.5,<5.0.0)
Project-URL: Repository, https://github.com/kdunee/quizgen
